Metadata-Version: 1.0
Name: ppy
Version: 0.1.0
Summary: Packaging for Python.
Home-page: http://github.com/joeyespo/ppy
Author: Joe Esposito
Author-email: joe@joeyespo.com
License: MIT
Platform: any
